sigil_mcp/__init__.py
sigil_mcp/__main__.py
sigil_mcp/admin_api.py
sigil_mcp/admin_api_main.py
sigil_mcp/admin_ui.py
sigil_mcp/app_factory.py
sigil_mcp/auth.py
sigil_mcp/config.py
sigil_mcp/embeddings.py
sigil_mcp/ignore_utils.py
sigil_mcp/indexer.py
sigil_mcp/llamacpp_provider.py
sigil_mcp/logging_setup.py
sigil_mcp/manage_auth.py
sigil_mcp/mcp_client.py
sigil_mcp/mcp_installer.py
sigil_mcp/oauth.py
sigil_mcp/py.typed
sigil_mcp/schema.py
sigil_mcp/server.py
sigil_mcp/watcher.py
sigil_mcp/middleware/header_logging.py
sigil_mcp/scripts/__init__.py
sigil_mcp/scripts/rebuild_indexes.py
sigil_mcp/security/__init__.py
sigil_mcp/security/auth.py
sigil_mcp_server-1.0.1.dist-info/licenses/LICENSE
sigil_mcp_server-1.0.1.dist-info/licenses/NOTICE
sigil_mcp_server-1.0.1.dist-info/METADATA
sigil_mcp_server-1.0.1.dist-info/WHEEL
sigil_mcp_server-1.0.1.dist-info/entry_points.txt
sigil_mcp_server-1.0.1.dist-info/top_level.txt
sigil_mcp_server-1.0.1.dist-info/RECORD
