Metadata-Version: 2.4
Name: sigil-mcp-server
Version: 1.0.1
Summary: Model Context Protocol server for IDE-like code navigation and semantic search
Author-email: Dave Tofflemire <davetmire85@gmail.com>
License: AGPL-3.0-or-later
Project-URL: Homepage, https://github.com/Superuser666-Sigil/SigilDERG-Custom-MCP
Project-URL: Documentation, https://github.com/Superuser666-Sigil/SigilDERG-Custom-MCP/tree/main/docs
Project-URL: Repository, https://github.com/Superuser666-Sigil/SigilDERG-Custom-MCP
Project-URL: Issues, https://github.com/Superuser666-Sigil/SigilDERG-Custom-MCP/issues
Keywords: mcp,model-context-protocol,code-search,semantic-search,vector-embeddings,trigram-index,ctags,ide-features
Classifier: Development Status :: 4 - Beta
Classifier: Intended Audience :: Developers
Classifier: License :: OSI Approved :: GNU Affero General Public License v3
Classifier: Operating System :: OS Independent
Classifier: Programming Language :: Python :: 3
Classifier: Programming Language :: Python :: 3.12
Classifier: Topic :: Software Development :: Libraries :: Python Modules
Classifier: Topic :: Text Processing :: Indexing
Classifier: Typing :: Typed
Requires-Python: >=3.12
License-File: LICENSE
License-File: NOTICE
Requires-Dist: mcp>=1.22.0
Requires-Dist: fastmcp>=2.14.0
Requires-Dist: numpy<3.0,>=1.24.0
Requires-Dist: rocksdict>=0.3.20
Provides-Extra: dev
Requires-Dist: pytest>=7.4.0; extra == "dev"
Requires-Dist: pytest-cov>=4.1.0; extra == "dev"
Requires-Dist: black>=23.0.0; extra == "dev"
Requires-Dist: ruff>=0.1.0; extra == "dev"
Requires-Dist: mypy>=1.5.0; extra == "dev"
Requires-Dist: httpx>=0.27.0; extra == "dev"
Requires-Dist: flake8>=7.0.0; extra == "dev"
Provides-Extra: watch
Requires-Dist: watchdog>=3.0.0; extra == "watch"
Provides-Extra: embeddings-sentencetransformers
Requires-Dist: sentence-transformers>=2.2.0; extra == "embeddings-sentencetransformers"
Requires-Dist: torch>=2.0.0; extra == "embeddings-sentencetransformers"
Provides-Extra: embeddings-openai
Requires-Dist: openai>=1.0.0; extra == "embeddings-openai"
Provides-Extra: embeddings-llamacpp-cpu
Requires-Dist: llama-cpp-python>=0.3.0; extra == "embeddings-llamacpp-cpu"
Provides-Extra: embeddings-llamacpp-cuda
Requires-Dist: llama-cpp-python[cuda]>=0.3.0; extra == "embeddings-llamacpp-cuda"
Provides-Extra: embeddings-llamacpp-rocm
Requires-Dist: llama-cpp-python[rocm]>=0.3.0; extra == "embeddings-llamacpp-rocm"
Provides-Extra: embeddings-llamacpp-metal
Requires-Dist: llama-cpp-python[metal]>=0.3.0; extra == "embeddings-llamacpp-metal"
Provides-Extra: lancedb
Requires-Dist: lancedb>=0.5.0; extra == "lancedb"
Requires-Dist: pyarrow>=14.0.0; extra == "lancedb"
Provides-Extra: embeddings-all
Requires-Dist: sentence-transformers>=2.2.0; extra == "embeddings-all"
Requires-Dist: torch>=2.0.0; extra == "embeddings-all"
Requires-Dist: openai>=1.0.0; extra == "embeddings-all"
Requires-Dist: llama-cpp-python>=0.3.0; extra == "embeddings-all"
Provides-Extra: server-full
Requires-Dist: watchdog>=3.0.0; extra == "server-full"
Requires-Dist: lancedb>=0.5.0; extra == "server-full"
Requires-Dist: pyarrow>=14.0.0; extra == "server-full"
Requires-Dist: llama-cpp-python>=0.3.0; extra == "server-full"
Dynamic: license-file
